LICENSE
README.md
setup.py
terminalpainter/__init__.py
terminalpainter/ansi.py
terminalpainter/canvas.py
terminalpainter/colors.py
terminalpainter/painter.py
terminalpainter.egg-info/PKG-INFO
terminalpainter.egg-info/SOURCES.txt
terminalpainter.egg-info/dependency_links.txt
terminalpainter.egg-info/requires.txt
terminalpainter.egg-info/top_level.txt