Metadata-Version: 2.1
Name: terminalpainter
Version: 1.0.0
Summary: Terminal painter
Home-page: https://github.com/professionalincpp/your_project
Author: professionalincpp
Author-email: griguchaev@yandex.ru
License: MIT
Classifier: Intended Audience :: Developers
Classifier: License :: OSI Approved :: MIT License
Classifier: Programming Language :: Python :: 3.10
Classifier: Programming Language :: Python :: 3.11
Classifier: Programming Language :: Python :: 3.12
Classifier: Topic :: Software Development :: Libraries :: Python Modules
Requires-Python: >=3.10
License-File: LICENSE
Requires-Dist: Pillow>=10.0.0
